jefer/main.py
jefer-0.1.0.dist-info/entry_points.txt
jefer-0.1.0.dist-info/LICENSE
jefer-0.1.0.dist-info/WHEEL
jefer-0.1.0.dist-info/METADATA
jefer-0.1.0.dist-info/RECORD
