Metadata-Version: 2.1
Name: jefer
Version: 0.1.0
Summary: A simple dotfiles manager written in asynchronous Python code.
License: MIT
Author: Somraj Saha
Author-email: somraj.mle@gmail.com
Requires-Python: >=3.10,<4.0
Classifier: License :: OSI Approved :: MIT License
Classifier: Programming Language :: Python :: 3
Classifier: Programming Language :: Python :: 3.10
Classifier: Programming Language :: Python :: 3.11
Requires-Dist: typer[all] (>=0.6.1,<0.7.0)
